counter.sv
module counter
(
	input 	logic 		clk,
	input 	logic 		rst,

	input 	logic 		enable,
	input 	logic 		sel,

	output 	logic 	[3:0]	out
);

always @(posedge clk or posedge rst)
begin
	if (rst)
	begin
		out <= 0;
	end
	else if (enable)
	begin
		out <= (sel) ?	out - 1 :
				out + 1;
	end
end

endmodule

top.sv
module top ();

logic clk;
logic rst;
logic enable;
logic sel;
logic [3:0] out;


initial
begin
	clk = 0;
	rst = 0;
	enable = 1;
	sel = 0;

	$dumpfile("wave.vcd");
	$dumpvars(0, top);
end

always #10 clk <= ~clk;

initial
begin
	#26 rst = 1;
	#71 rst = 0;
	#122 sel = 1;
	#70 enable = 0;
	#141 enable = 1;
	#100 sel = 0;
	#100 $finish;
end

counter ctr
(
	.clk(clk),
	.rst(rst),

	.enable(enable),
	
	.sel(sel),

	.out(out)
);

endmodule

sim/wave.vcd
$version Generated by VerilatedVcd $end
$timescale 1ps $end

 $scope module TOP $end
  $scope module top $end
   $var wire  1 # clk $end
   $var wire  1 % enable $end
   $var wire  4 ' out [3:0] $end
   $var wire  1 $ rst $end
   $var wire  1 & sel $end
   $scope module ctr $end
    $var wire  1 # clk $end
    $var wire  1 % enable $end
    $var wire  4 ' out [3:0] $end
    $var wire  1 $ rst $end
    $var wire  1 & sel $end
   $upscope $end
  $upscope $end
 $upscope $end
$enddefinitions $end


#1
0#
0$
1%
0&
b0000 '
#2
#3
#4
#5
#6
#7
#8
#9
#10
#11
1#
b0001 '
#12
#13
#14
#15
#16
#17
#18
#19
#20
#21
0#
#22
#23
#24
#25
#26
#27
1$
b0000 '
#28
#29
#30
#31
1#
#32
#33
#34
#35
#36
#37
#38
#39
#40
#41
0#
#42
#43
#44
#45
#46
#47
#48
#49
#50
#51
1#
#52
#53
#54
#55
#56
#57
#58
#59
#60
#61
0#
#62
#63
#64
#65
#66
#67
#68
#69
#70
#71
1#
#72
#73
#74
#75
#76
#77
#78
#79
#80
#81
0#
#82
#83
#84
#85
#86
#87
#88
#89
#90
#91
1#
#92
#93
#94
#95
#96
#97
#98
0$
#99
#100
#101
0#
#102
#103
#104
#105
#106
#107
#108
#109
#110
#111
1#
b0001 '
#112
#113
#114
#115
#116
#117
#118
#119
#120
#121
0#
#122
#123
#124
#125
#126
#127
#128
#129
#130
#131
1#
b0010 '
#132
#133
#134
#135
#136
#137
#138
#139
#140
#141
0#
#142
#143
#144
#145
#146
#147
#148
#149
#150
#151
1#
b0011 '
#152
#153
#154
#155
#156
#157
#158
#159
#160
#161
0#
#162
#163
#164
#165
#166
#167
#168
#169
#170
#171
1#
b0100 '
#172
#173
#174
#175
#176
#177
#178
#179
#180
#181
0#
#182
#183
#184
#185
#186
#187
#188
#189
#190
#191
1#
b0101 '
#192
#193
#194
#195
#196
#197
#198
#199
#200
#201
0#
#202
#203
#204
#205
#206
#207
#208
#209
#210
#211
1#
b0110 '
#212
#213
#214
#215
#216
#217
#218
#219
#220
1&
#221
0#
#222
#223
#224
#225
#226
#227
#228
#229
#230
#231
1#
b0101 '
#232
#233
#234
#235
#236
#237
#238
#239
#240
#241
0#
#242
#243
#244
#245
#246
#247
#248
#249
#250
#251
1#
b0100 '
#252
#253
#254
#255
#256
#257
#258
#259
#260
#261
0#
#262
#263
#264
#265
#266
#267
#268
#269
#270
#271
1#
b0011 '
#272
#273
#274
#275
#276
#277
#278
#279
#280
#281
0#
#282
#283
#284
#285
#286
#287
#288
#289
#290
0%
